setup.py
checkemail/__init__.py
checkemail/checkemail.py
checkemail.egg-info/PKG-INFO
checkemail.egg-info/SOURCES.txt
checkemail.egg-info/dependency_links.txt
checkemail.egg-info/not-zip-safe
checkemail.egg-info/top_level.txt