Metadata-Version: 2.1
Name: checkemail
Version: 0.3
Summary: Validate domain of email
Author: online1004
Author-email: contact@online1004.xyz
